pyqgis_scripting_ext/__init__.py
pyqgis_scripting_ext/core.py
pyqgis_scripting_ext-0.1.1.dist-info/WHEEL
pyqgis_scripting_ext-0.1.1.dist-info/METADATA
pyqgis_scripting_ext-0.1.1.dist-info/licenses/LICENSE
pyqgis_scripting_ext-0.1.1.dist-info/RECORD
