Metadata-Version: 2.1
Name: pyqgis-scripting-ext
Version: 0.1.1
Summary: A simple package that tries to make pyQGIS a bit more userfriendly to non programmers.
License: MIT
Author: Andrea Antonello
Requires-Python: >=3.8
Project-URL: homepage, https://github.com/moovida/pyqgis_scripting_extensions.git
Project-URL: repository, https://github.com/moovida/pyqgis_scripting_extensions.git
